geodesic/__init__.py
geodesic/auth.py
geodesic/bases.py
geodesic/client.py
geodesic/config.py
geodesic/context.py
geodesic/cql.py
geodesic/descriptors.py
geodesic/service.py
geodesic/stac.py
geodesic/account/__init__.py
geodesic/account/api_keys.py
geodesic/account/credentials.py
geodesic/account/oauth2.py
geodesic/account/organizations.py
geodesic/account/projects.py
geodesic/account/tokens.py
geodesic/account/user.py
geodesic/admin/__init__.py
geodesic/boson/__init__.py
geodesic/boson/asset_bands.py
geodesic/boson/boson.py
geodesic/boson/command_status.py
geodesic/boson/dataset.py
geodesic/boson/dataset_info.py
geodesic/boson/middleware.py
geodesic/boson/servicer_settings.py
geodesic/boson/tile_options.py
geodesic/cli/__init__.py
geodesic/cli/build_graph.py
geodesic/cli/build_project.py
geodesic/cli/cli.py
geodesic/entanglement/__init__.py
geodesic/entanglement/graph.py
geodesic/entanglement/graphql.py
geodesic/entanglement/object.py
geodesic/experimental/__init__.py
geodesic/experimental/base.py
geodesic/experimental/registry.py
geodesic/experimental/ontology/__init__.py
geodesic/experimental/ontology/linkml.py
geodesic/experimental/ontology/mappings.py
geodesic/experimental/ontology/ontology.py
geodesic/experimental/ontology/search.py
geodesic/mapping/__init__.py
geodesic/mapping/base.py
geodesic/tesseract/__init__.py
geodesic/tesseract/components.py
geodesic/tesseract/job.py
geodesic/tesseract/regex.py
geodesic/tesseract/utils.py
geodesic/utils/__init__.py
geodesic/utils/backoff.py
geodesic/utils/display.py
geodesic/utils/exif.py
geodesic/utils/gdal_utils.py
geodesic/utils/memcache.py
geodesic/widgets/__init__.py
geodesic/widgets/asset_bands_widget.py
geodesic/widgets/cql_filter.py
geodesic/widgets/dataset_explorer.py
geodesic/widgets/header_widget.py
geodesic_api-1.17.6.dist-info/licenses/LICENSE
geodesic_api-1.17.6.dist-info/METADATA
geodesic_api-1.17.6.dist-info/WHEEL
geodesic_api-1.17.6.dist-info/entry_points.txt
geodesic_api-1.17.6.dist-info/top_level.txt
geodesic_api-1.17.6.dist-info/RECORD
