Metadata-Version: 2.4
Name: geodesic-api
Version: 1.17.6
Summary: Python API for the Geodesic Datascience Platform
Author-email: The SeerAI Team <contact@seer.ai>
License:                                  Apache License
Project-URL: Homepage, https://docs.seerai.space/geodesic
Keywords: geodesic,analysis,seerai,data,science
Classifier: Programming Language :: Python
Classifier: Operating System :: OS Independent
Classifier: Intended Audience :: Developers
Classifier: Intended Audience :: Science/Research
Classifier: Topic :: Scientific/Engineering :: GIS
Classifier: Topic :: Scientific/Engineering :: Visualization
Classifier: Topic :: Scientific/Engineering :: Artificial Intelligence
Classifier: Topic :: Software Development :: Libraries :: Python Modules
Classifier: License :: OSI Approved :: Apache Software License
Requires-Python: >=3.7
License-File: LICENSE
Requires-Dist: requests<3.0,>=2.26
Requires-Dist: six>=1.16
Requires-Dist: shapely>=1.7
Requires-Dist: numpy<2.0,>=1.8
Requires-Dist: pytz>=2021.1
Requires-Dist: python-dateutil~=2.8
Requires-Dist: tenacity~=8.0
Requires-Dist: wrapt~=1.12
Requires-Dist: pyjwt~=1.7
Requires-Dist: tqdm>=4.62
Requires-Dist: geopandas>=0.9.0
Requires-Dist: retry>=0.9.2
Requires-Dist: ruamel.yaml<0.18.0
Requires-Dist: rich~=12.6.0
Requires-Dist: click>=8.0
Requires-Dist: prettytable==3.16.0
Provides-Extra: all
Requires-Dist: geodesic-api[jupyter]; extra == "all"
Requires-Dist: geodesic-api[entanglement]; extra == "all"
Requires-Dist: geodesic-api[tesseract]; extra == "all"
Requires-Dist: geodesic-api[geopandas]; extra == "all"
Provides-Extra: dev
Requires-Dist: geodesic-api[all]; extra == "dev"
Requires-Dist: pytest>=6.2.5; extra == "dev"
Requires-Dist: coverage>=5.5; extra == "dev"
Requires-Dist: ruff; extra == "dev"
Requires-Dist: pre-commit; extra == "dev"
Requires-Dist: pyshp>=2.0.0; extra == "dev"
Requires-Dist: fiona>=1.0; extra == "dev"
Provides-Extra: jupyter
Requires-Dist: ipykernel>=6.3; extra == "jupyter"
Requires-Dist: ipywidgets<9.0,>=7.7; extra == "jupyter"
Requires-Dist: jupyterlab<4,>=3; extra == "jupyter"
Requires-Dist: matplotlib<3.7; extra == "jupyter"
Requires-Dist: ipympl~=0.9.3; extra == "jupyter"
Requires-Dist: ipyleaflet>=0.14; extra == "jupyter"
Requires-Dist: descartes>=1.1; extra == "jupyter"
Requires-Dist: Pillow>=8.3; extra == "jupyter"
Provides-Extra: entanglement
Requires-Dist: networkx~=2.0; extra == "entanglement"
Provides-Extra: tesseract
Requires-Dist: geodesic-api[entanglement]; extra == "tesseract"
Requires-Dist: zarr<3.0,>=2.16; extra == "tesseract"
Requires-Dist: fsspec; extra == "tesseract"
Dynamic: license-file
